piper/__init__.py
piper/custom.py
piper/decorators.py
piper/defaults.py
piper/factory.py
piper/io.py
piper/jde.py
piper/magics.py
piper/nb.py
piper/odbc.py
piper/sql.py
piper/styler.py
piper/text.py
piper/utils.py
piper/verbs.py
piper/version.py
piper/xl.py
piper/test/__init__.py
piper/test/test_custom.py
piper/test/test_decorators.py
piper/test/test_io.py
piper/test/test_jde.py
piper/test/test_magics.py
piper/test/test_odbc.py
piper/test/test_sql.py
piper/test/test_styler.py
piper/test/test_text.py
piper/test/test_utils.py
piper/test/test_verbs.py
piper/test/test_xl.py
dpiper-0.1.2.dist-info/LICENSE.txt
dpiper-0.1.2.dist-info/METADATA
dpiper-0.1.2.dist-info/WHEEL
dpiper-0.1.2.dist-info/top_level.txt
dpiper-0.1.2.dist-info/RECORD
