Metadata-Version: 2.1
Name: dpiper
Version: 0.1.2
Summary: A Python module for maintaining pipeline syntax of Pandas statements.
Home-page: https://github.com/miketarpey/piper
Author: Mike Tarpey
Author-email: miketarpey@gmx.net
License: BSD
Platform: UNKNOWN
Classifier: Development Status :: 3 - Alpha
Classifier: License :: OSI Approved :: BSD License
Classifier: Programming Language :: Python
Classifier: Programming Language :: Python :: 3.7
Classifier: Programming Language :: Python :: 3.8
Classifier: Programming Language :: Python :: 3.9
Requires-Dist: cx-oracle
Requires-Dist: numpy (>=1.20.0)
Requires-Dist: openpyxl (>=3.0.6)
Requires-Dist: pandas (>=1.0.0)
Requires-Dist: psycopg2
Requires-Dist: pypyodbc
Requires-Dist: seaborn (>=0.11.1)
Requires-Dist: xlsxwriter (>=1.3.2)
